django_debug_toolbar_template_timings-0.9.dist-info/DESCRIPTION.rst
django_debug_toolbar_template_timings-0.9.dist-info/METADATA
django_debug_toolbar_template_timings-0.9.dist-info/RECORD
django_debug_toolbar_template_timings-0.9.dist-info/WHEEL
django_debug_toolbar_template_timings-0.9.dist-info/metadata.json
django_debug_toolbar_template_timings-0.9.dist-info/top_level.txt
template_timings_panel/__init__.py
template_timings_panel/panels/TemplateTimings.py
template_timings_panel/panels/__init__.py
template_timings_panel/templates/debug_toolbar_template_timings.html
