Metadata-Version: 2.0
Name: django-debug-toolbar-template-timings
Version: 0.9
Summary: A django-debug-toolbar panel that shows you template rendering times for Django
Home-page: https://github.com/orf/django-debug-toolbar-template-timings
Author: Tom Forbes
Author-email: tom@tomforb.es
License: The MIT License (MIT)
Requires-Dist: Django
Requires-Dist: django-debug-toolbar (>=1.0)
